hts/__init__.py
hts/_t.py
hts/convenience.py
hts/defaults.py
hts/functions.py
hts/revision.py
hts/transforms.py
hts/core/__init__.py
hts/core/exceptions.py
hts/core/regressor.py
hts/core/result.py
hts/core/utils.py
hts/hierarchy/__init__.py
hts/hierarchy/utils.py
hts/model/__init__.py
hts/model/ar.py
hts/model/base.py
hts/model/es.py
hts/model/p.py
hts/utilities/__init__.py
hts/utilities/distribution.py
hts/utilities/load_data.py
hts/utilities/utils.py
hts/viz/__init__.py
hts/viz/geo.py
scikit_hts-0.5.12.dist-info/LICENSE
scikit_hts-0.5.12.dist-info/METADATA
scikit_hts-0.5.12.dist-info/WHEEL
scikit_hts-0.5.12.dist-info/top_level.txt
scikit_hts-0.5.12.dist-info/RECORD
