Metadata-Version: 2.1
Name: scikit-hts
Version: 0.5.12
Summary: Hierarchical Time Series forecasting
Home-page: UNKNOWN
Author: Carlo Mazzaferro
Author-email: carlo.mazzaferro@gmail.com
License: UNKNOWN
Keywords: scikit-hts
Platform: UNKNOWN
Classifier: Development Status :: 3 - Alpha
Classifier: Intended Audience :: Developers
Classifier: Natural Language :: English
Classifier: Programming Language :: Python :: 3.7
Classifier: Programming Language :: Python :: 3.8
Provides-Extra: test
Provides-Extra: geo
Provides-Extra: prophet
Provides-Extra: distributed
Provides-Extra: dev
Provides-Extra: auto_arima
Provides-Extra: all
